atflagger.py
atflagger-0.4.6.dist-info/entry_points.txt
atflagger-0.4.6.dist-info/LICENSE
atflagger-0.4.6.dist-info/WHEEL
atflagger-0.4.6.dist-info/METADATA
atflagger-0.4.6.dist-info/RECORD
