Metadata-Version: 2.1
Name: atflagger
Version: 0.4.6
Summary: Simple method for flagging UWL data.
License: MIT
Author: Alec Thomson
Requires-Python: >=3.8,<4.0
Classifier: License :: OSI Approved :: MIT License
Classifier: Programming Language :: Python :: 3
Classifier: Programming Language :: Python :: 3.8
Classifier: Programming Language :: Python :: 3.9
Classifier: Programming Language :: Python :: 3.10
Classifier: Programming Language :: Python :: 3.11
Requires-Dist: astropy (>=5,<6)
Requires-Dist: bokeh
Requires-Dist: dask (>=2022,<2023)
Requires-Dist: distributed (>=2022,<2023)
Requires-Dist: h5py
Requires-Dist: matplotlib
Requires-Dist: numpy
Requires-Dist: tqdm
Requires-Dist: xarray
